recovid/__init__.py
recovid/data/__init__.py
recovid/data/paper.py
recovid/utils/__init__.py
recovid/utils/utils.py
recovid-0.0.1.dist-info/LICENSE
recovid-0.0.1.dist-info/METADATA
recovid-0.0.1.dist-info/WHEEL
recovid-0.0.1.dist-info/top_level.txt
recovid-0.0.1.dist-info/RECORD
