Metadata-Version: 2.1
Name: recovid
Version: 0.0.1
Summary: Researching COVID-19 Open Research Dataset Challenge (CORD-19)
Home-page: https://github.com/amrmkayid/recovid
Author: Amr Kayid
Author-email: amrmkayid@gmail.com
License: UNKNOWN
Platform: UNKNOWN
Classifier: Programming Language :: Python :: 3
Classifier: License :: OSI Approved :: MIT License
Classifier: Operating System :: OS Independent
